algotype/__init__.py
algotype/afm_lib.py
algotype/afm_parse.py
algotype/algotype.py
algotype/at_lib.py
algotype/config.py
algotype/config_interpreter.py
algotype/enc_map_lib.py
algotype/fea_rename.py
algotype/ffdklib3.py
algotype/goadb_lib.py
algotype/json_font_lib.py
algotype/kern_lib.py
algotype/lm_fea.py
algotype/log_lib.py
algotype/make_algotype_ff.py
algotype/meta.py
algotype/oti2enc3.py
algotype/oti2fea3.py
algotype/parse_config.py
algotype/parse_eps.py
algotype/pfb_lib.py
algotype/rename_lib.py
algotype/run_lib.py
algotype/steps.py
algotype/time_lib.py
algotype-0.2.39.dist-info/LICENCE.txt
algotype-0.2.39.dist-info/METADATA
algotype-0.2.39.dist-info/WHEEL
algotype-0.2.39.dist-info/entry_points.txt
algotype-0.2.39.dist-info/top_level.txt
algotype-0.2.39.dist-info/RECORD
