Metadata-Version: 2.1
Name: algotype
Version: 0.2.39
Summary: Algorythmic font creation system.
Home-page: http://algotype.org
Author: Marek Ryćko, Bogusław Jackowski, Piotr Strzelczyk
Author-email: marek@do.com.pl
Maintainer: Marek Ryćko
Maintainer-email: marek@do.com.pl
License: UNKNOWN
Platform: UNKNOWN
Classifier: Development Status :: 3 - Alpha
Classifier: License :: OSI Approved :: MIT License
Classifier: Programming Language :: Python :: 3
Classifier: Operating System :: OS Independent
Requires-Python: >=3.6
